easyjson2/__init__.py
easyjson2/parser.py
easyjson2-0.1.1.dist-info/METADATA
easyjson2-0.1.1.dist-info/WHEEL
easyjson2-0.1.1.dist-info/top_level.txt
easyjson2-0.1.1.dist-info/RECORD
