Metadata-Version: 2.1
Name: easyjson2
Version: 0.1.1
Summary: Get JSON quickly and easily
Home-page: https://github.com/RunningIkkyu/easy-json
Author: RunningIkkyu
Author-email: 389498623@qq.com
License: MIT
Platform: UNKNOWN
Classifier: Intended Audience :: Developers
Classifier: Programming Language :: Python :: 3
Classifier: Programming Language :: Python :: 3.6
Classifier: Programming Language :: Python :: 3.7
Classifier: Programming Language :: Python :: 3.8
Classifier: Programming Language :: Python :: 3.9
